{"cameraMode":{"drawMode":0,"name":"Shaded","section":"Shading Mode"},"sceneLighting":true,"audioPlay":false,"sceneViewState":{"showFog":true,"showMaterialUpdate":false,"showSkybox":true,"showFlares":true,"showImageEffects":true,"showParticleSystems":true},"in2DMode":false,"pivot":{"x":60.7376708984375,"y":10.464445114135743,"z":46.350345611572269},"rotation":{"x":0.1775737851858139,"y":-0.6283217072486877,"z":0.15060923993587495,"w":0.7428549528121948},"size":31.172149658203126,"orthographic":false}